langchain_openai_limiter/__init__.py
langchain_openai_limiter/capture_headers.py
langchain_openai_limiter/choose_key_chat_openai.py
langchain_openai_limiter/choose_key_openai_embeddings.py
langchain_openai_limiter/limit_await_chat_openai.py
langchain_openai_limiter/limit_await_openai_embeddings.py
langchain_openai_limiter/limit_info.py
langchain_openai_limiter/reset_time_parser.py
langchain_openai_limiter-0.0.2.dist-info/LICENSE
langchain_openai_limiter-0.0.2.dist-info/METADATA
langchain_openai_limiter-0.0.2.dist-info/WHEEL
langchain_openai_limiter-0.0.2.dist-info/top_level.txt
langchain_openai_limiter-0.0.2.dist-info/RECORD
